evernote/__init__.py
evernote/edam/__init__.py
evernote/edam/error/__init__.py
evernote/edam/error/constants.py
evernote/edam/error/ttypes.py
evernote/edam/limits/__init__.py
evernote/edam/limits/constants.py
evernote/edam/limits/ttypes.py
evernote/edam/notestore/NoteStore.py
evernote/edam/notestore/__init__.py
evernote/edam/notestore/constants.py
evernote/edam/notestore/ttypes.py
evernote/edam/type/__init__.py
evernote/edam/type/constants.py
evernote/edam/type/ttypes.py
evernote/edam/userstore/UserStore.py
evernote/edam/userstore/__init__.py
evernote/edam/userstore/constants.py
evernote/edam/userstore/ttypes.py
evernote_plus-1.28.1.dev2.dist-info/LICENSE
evernote_plus-1.28.1.dev2.dist-info/LICENSE-APACHE-2.0.txt
evernote_plus-1.28.1.dev2.dist-info/METADATA
evernote_plus-1.28.1.dev2.dist-info/NOTICE
evernote_plus-1.28.1.dev2.dist-info/WHEEL
evernote_plus-1.28.1.dev2.dist-info/RECORD
